setup.py
pped/PPE.py
pped/__init__.py
pped.egg-info/PKG-INFO
pped.egg-info/SOURCES.txt
pped.egg-info/dependency_links.txt
pped.egg-info/not-zip-safe
pped.egg-info/top_level.txt