Metadata-Version: 1.0
Name: pped
Version: 1.1
Summary: ppe detection
Home-page: UNKNOWN
Author: Ahmed Safwat Ewida
Author-email: UNKNOWN
License: UNKNOWN
Platform: UNKNOWN
